README.md
setup.py
fungjokeb/__init__.py
fungjokeb/main.py
fungjokeb.egg-info/PKG-INFO
fungjokeb.egg-info/SOURCES.txt
fungjokeb.egg-info/dependency_links.txt
fungjokeb.egg-info/top_level.txt