Metadata-Version: 2.1
Name: fungjokeb
Version: 0.0.1
Summary: A small example package
Home-page: https://github.com/pypa/sampleproject
Author: fung
Author-email: fungjoke@gmail.com.com
License: UNKNOWN
Platform: UNKNOWN
Classifier: Programming Language :: Python :: 2.7
Classifier: License :: OSI Approved :: MIT License
Classifier: Operating System :: OS Independent
Requires-Python: >=2.7
